data/__init__.py
tests/__init__.py
tests/test_shift_and_stack.py
tests/data/__init__.py
shift_stack_moons-0.1.0.dist-info/LICENSE.txt
shift_stack_moons-0.1.0.dist-info/METADATA
shift_stack_moons-0.1.0.dist-info/WHEEL
shift_stack_moons-0.1.0.dist-info/top_level.txt
shift_stack_moons-0.1.0.dist-info/RECORD
