Metadata-Version: 2.1
Name: shift_stack_moons
Version: 0.1.0
Summary: Find small moons around planets     using shift-and-stack based on JPL Horizons ephemeris
Home-page: https://github.com/emolter/shift_stack_moons
Author: Ned Molter
Author-email: emolter@berkeley.edu
License: BSD
Keywords: planetary astronomy moons jpl ephemeris
Platform: any
Classifier: Development Status :: 3 - Alpha
Classifier: Intended Audience :: Science/Research
Classifier: License :: OSI Approved :: BSD License
Classifier: Programming Language :: Python
Classifier: Programming Language :: Python :: 3.6
Classifier: Programming Language :: Python :: 3.7
Classifier: Programming Language :: Python :: 3.8
Classifier: Programming Language :: Python :: 3.9
Classifier: Programming Language :: Python :: 3.10
Classifier: Programming Language :: Python :: 3.11
Classifier: Topic :: Software Development :: Libraries :: Python Modules
Requires-Python: >=3
License-File: LICENSE.txt
